Metadata-Version: 1.1
Name: plotlyhtmlexporter
Version: 0.0.2
Summary: Plotly friendly, Jupyter Notebook HTML Exporter.
Home-page: https://plot.ly/ipython-notebooks/
Author: Tarun G
Author-email: tarun@plot.ly
License: MIT
Platform: UNKNOWN
Classifier: Development Status :: 4 - Beta
Classifier: Programming Language :: Python :: 2
Classifier: Programming Language :: Python :: 2.7
Classifier: Programming Language :: Python :: 3
Classifier: Programming Language :: Python :: 3.3
Classifier: Programming Language :: Python :: 3.4
Classifier: Programming Language :: Python :: 3.5
Classifier: Topic :: Scientific/Engineering :: Visualization
